soccertrack/__init__.py
soccertrack/camera/__init__.py
soccertrack/camera/camera.py
soccertrack/checks.py
soccertrack/cli.py
soccertrack/dataframe/__init__.py
soccertrack/dataframe/base.py
soccertrack/dataframe/bboxdataframe.py
soccertrack/dataframe/coordinatesdataframe.py
soccertrack/dataframe/gpsdataframe.py
soccertrack/datasets/__init__.py
soccertrack/datasets/downloader.py
soccertrack/datasets/labelbox_uploader.py
soccertrack/detection_model/__init__.py
soccertrack/detection_model/base.py
soccertrack/detection_model/yolov5.py
soccertrack/image_model/__init__.py
soccertrack/image_model/torchreid.py
soccertrack/image_model/visualization.py
soccertrack/io/__init__.py
soccertrack/io/file.py
soccertrack/logger.py
soccertrack/metrics/__init__.py
soccertrack/metrics/cost_matrix_metrics.py
soccertrack/metrics/hota.py
soccertrack/metrics/identity.py
soccertrack/metrics/mota.py
soccertrack/metrics/object_detection.py
soccertrack/metrics/tracking_preprocess.py
soccertrack/metrics/utils.py
soccertrack/pipeline.py
soccertrack/tracking_model/__init__.py
soccertrack/tracking_model/base.py
soccertrack/tracking_model/matching.py
soccertrack/tracking_model/multi_object_tracker.py
soccertrack/tracking_model/single_object_tracker.py
soccertrack/tracking_model/tracker.py
soccertrack/types.py
soccertrack/utils/__init__.py
soccertrack/utils/detection.py
soccertrack/utils/draw.py
soccertrack/utils/track.py
soccertrack/utils/tracking.py
soccertrack/utils/utils.py
soccertrack-0.2.3.dist-info/LICENSE
soccertrack-0.2.3.dist-info/METADATA
soccertrack-0.2.3.dist-info/WHEEL
soccertrack-0.2.3.dist-info/RECORD
