Metadata-Version: 2.1
Name: soccertrack
Version: 0.2.3
Summary: A dataset and algorithm for multi-object tracking in sports
License: LICENSE
Author: Atom Scott
Author-email: atom.james.scott@gmail.com
Requires-Python: >=3.9,<3.11
Classifier: License :: Other/Proprietary License
Classifier: Programming Language :: Python :: 3
Classifier: Programming Language :: Python :: 3.9
Classifier: Programming Language :: Python :: 3.10
Requires-Dist: ffmpeg-python (>=0.2.0,<0.3.0)
Requires-Dist: filterpy (>=1.4.5,<2.0.0)
Requires-Dist: furo (>=2022.6.21,<2023.0.0)
Requires-Dist: gdown (>=4.6.0,<5.0.0)
Requires-Dist: gitpython (>=3.1.30,<4.0.0)
Requires-Dist: ipython (>=8.5.0,<9.0.0)
Requires-Dist: ipywidgets (>=8.0.4,<9.0.0)
Requires-Dist: jupyter (>=1.0.0,<2.0.0)
Requires-Dist: kaggle (>=1.5.12,<2.0.0)
Requires-Dist: labelbox (>=3.35.0,<4.0.0)
Requires-Dist: loguru (>=0.6.0,<0.7.0)
Requires-Dist: motpy (>=0.0.10,<0.0.11)
Requires-Dist: mplsoccer (>=1.1.10,<2.0.0)
Requires-Dist: nbsphinx (>=0.8.9,<0.9.0)
Requires-Dist: ndjson (>=0.3.1,<0.4.0)
Requires-Dist: numpy (>=1.22.4,<2.0.0)
Requires-Dist: omegaconf (>=2.2.2,<3.0.0)
Requires-Dist: opencv-contrib-python (>=4.6.0,<5.0.0)
Requires-Dist: pandas (>=1.4.2,<2.0.0)
Requires-Dist: poetry[seedir] (>=1.3.1,<2.0.0)
Requires-Dist: protobuf (>=3.20.0,<3.21.0)
Requires-Dist: pytest (>=7.1.2,<8.0.0)
Requires-Dist: python-dotenv (>=0.21.1,<0.22.0)
Requires-Dist: rich (>=12.5.1,<13.0.0)
Requires-Dist: scikit-learn (>=1.2.1,<2.0.0)
Requires-Dist: scikit-video (>=1.1.11,<2.0.0)
Requires-Dist: scipy (>=1.8.1,<2.0.0)
Requires-Dist: seedir (>=0.4.2,<0.5.0)
Requires-Dist: sphinx-autodoc-typehints (>=1.20.1,<2.0.0)
Requires-Dist: tensorboard (>=2.11.2,<3.0.0)
Requires-Dist: vidgear[core] (>=0.3.0,<0.4.0)
